maggtomic/__init__.py
maggtomic/query.py
maggtomic/util.py
maggtomic/harvester/__init__.py
maggtomic/harvester/pathmachine.py
maggtomic/harvester/s3.py
maggtomic-0.1.6.dist-info/LICENSE
maggtomic-0.1.6.dist-info/METADATA
maggtomic-0.1.6.dist-info/WHEEL
maggtomic-0.1.6.dist-info/top_level.txt
maggtomic-0.1.6.dist-info/RECORD
