Metadata-Version: 2.1
Name: maggtomic
Version: 0.1.6
Summary: Metadata aggregation using the Datomic information model
Home-page: https://github.com/polyneme/maggtomic
Author: Donny Winston
Author-email: donny@polyneme.xyz
License: UNKNOWN
Platform: UNKNOWN
Classifier: Development Status :: 1 - Planning
Classifier: Development Status :: 2 - Pre-Alpha
Classifier: Programming Language :: Python :: 3
Classifier: License :: OSI Approved :: BSD License
Requires-Python: >=3.6
Requires-Dist: base32-lib
Requires-Dist: boto3
Requires-Dist: pydash
Requires-Dist: pymongo
Requires-Dist: python-dotenv
Requires-Dist: toolz
